cdqspy/__init__.py
cdqspy/configs/__init__.py
cdqspy/configs/log_config.py
cdqspy/consts/__init__.py
cdqspy/consts/common_vars.py
cdqspy/consts/config_vars.py
cdqspy/models/__init__.py
cdqspy/models/nc_query_objs.py
cdqspy/models/nc_result_objs.py
cdqspy/service/__init__.py
cdqspy/service/query_nc_service.py
cdqspy/utils/__init__.py
cdqspy/utils/common_util.py
cdqspy/utils/nc_query_util.py
cdqspy-0.1.0.dist-info/LICENSE
cdqspy-0.1.0.dist-info/METADATA
cdqspy-0.1.0.dist-info/WHEEL
cdqspy-0.1.0.dist-info/top_level.txt
cdqspy-0.1.0.dist-info/RECORD
